av/utils.pxd
av/frame.pxd
av/logging.cpython-310-darwin.so
av/descriptor.pxd
av/stream.cpython-310-darwin.so
av/bytesource.cpython-310-darwin.so
av/logging.pxd
av/format.pxd
av/deprecation.py
av/dictionary.cpython-310-darwin.so
av/__init__.pxd
av/descriptor.cpython-310-darwin.so
av/error.pxd
av/datasets.py
av/buffer.pxd
av/packet.pxd
av/__init__.py
av/plane.cpython-310-darwin.so
av/bytesource.pxd
av/about.py
av/error.cpython-310-darwin.so
av/option.cpython-310-darwin.so
av/enum.pxd
av/enum.cpython-310-darwin.so
av/option.pxd
av/format.cpython-310-darwin.so
av/packet.cpython-310-darwin.so
av/buffer.cpython-310-darwin.so
av/stream.pxd
av/utils.cpython-310-darwin.so
av/frame.cpython-310-darwin.so
av/dictionary.pxd
av/__main__.py
av/plane.pxd
av/_core.cpython-310-darwin.so
av/video/frame.pxd
av/video/stream.cpython-310-darwin.so
av/video/reformatter.pxd
av/video/format.pxd
av/video/__init__.pxd
av/video/codeccontext.cpython-310-darwin.so
av/video/__init__.py
av/video/reformatter.cpython-310-darwin.so
av/video/plane.cpython-310-darwin.so
av/video/format.cpython-310-darwin.so
av/video/codeccontext.pxd
av/video/stream.pxd
av/video/frame.cpython-310-darwin.so
av/video/plane.pxd
av/bitstream/context.pxd
av/bitstream/__init__.py
av/bitstream/filter.pxd
av/bitstream/filter.cpython-310-darwin.so
av/bitstream/context.cpython-310-darwin.so
av/codec/__init__.pxd
av/codec/context.pxd
av/codec/codec.cpython-310-darwin.so
av/codec/__init__.py
av/codec/codec.pxd
av/codec/context.cpython-310-darwin.so
av/.dylibs/libtheoraenc.1.dylib
av/.dylibs/libvpx.7.dylib
av/.dylibs/libavformat.59.27.100.dylib
av/.dylibs/libaom.3.2.0.dylib
av/.dylibs/libxml2.2.dylib
av/.dylibs/libvorbisenc.2.dylib
av/.dylibs/libdav1d.5.dylib
av/.dylibs/libx264.164.dylib
av/.dylibs/libX11.6.dylib
av/.dylibs/libtheoradec.1.dylib
av/.dylibs/libtwolame.0.dylib
av/.dylibs/libpng16.16.dylib
av/.dylibs/libmp3lame.0.dylib
ha_av-10.1.2.dist-info/RECORD
ha_av-10.1.2.dist-info/WHEEL
ha_av-10.1.2.dist-info/entry_points.txt
ha_av-10.1.2.dist-info/AUTHORS.rst
ha_av-10.1.2.dist-info/AUTHORS.py
ha_av-10.1.2.dist-info/top_level.txt
ha_av-10.1.2.dist-info/LICENSE.txt
ha_av-10.1.2.dist-info/METADATA
